refractiveindex/__init__.py
refractiveindex/refractiveindex.py
refractiveindex-0.0.5.dist-info/LICENSE
refractiveindex-0.0.5.dist-info/METADATA
refractiveindex-0.0.5.dist-info/WHEEL
refractiveindex-0.0.5.dist-info/RECORD
