Metadata-Version: 2.1
Name: refractiveindex
Version: 0.0.5
Summary: 
Author: Ivan Toftul
Author-email: toftul.ivan@gmail.com
Requires-Python: >=3.10,<4.0
Classifier: Programming Language :: Python :: 3
Classifier: Programming Language :: Python :: 3.10
Classifier: Programming Language :: Python :: 3.11
Classifier: Programming Language :: Python :: 3.12
Requires-Dist: pyyaml (>=6.0,<7.0)
Requires-Dist: scipy (>=1.9.3,<2.0.0)
